<PAMDataset>
  <SRS>PROJCS["NAD_1983_2011_Oregon_Statewide_Lambert_Ft_Intl",GEOGCS["GCS_NAD_1983_2011",DATUM["NAD_1983_2011",SPHEROID["GRS_1980",6378137.0,298.257222101]],PRIMEM["Greenwich",0.0],UNIT["Degree",0.0174532925199433]],PROJECTION["Lambert_Conformal_Conic_2SP"],PARAMETER["False_Easting",1312335.958005249],PARAMETER["False_Northing",0.0],PARAMETER["Central_Meridian",-120.5],PARAMETER["Standard_Parallel_1",43.0],PARAMETER["Standard_Parallel_2",45.5],PARAMETER["Latitude_Of_Origin",41.75],UNIT["Foot",0.3048],AUTHORITY["EPSG","6557"]]</SRS>
  <Metadata domain="Esri">
    <MDI key="PyramidResamplingType">NEAREST</MDI>
  </Metadata>
  <Metadata domain="xml:ESRI" format="xml">
    <GeodataXform xsi:type="typens:PolynomialXform" xmlns:xsi="http://www.w3.org/2001/XMLSchema-instance" xmlns:xs="http://www.w3.org/2001/XMLSchema" xmlns:typens="http://www.esri.com/schemas/ArcGIS/10.6">
      <PolynomialOrder>1</PolynomialOrder>
      <SpatialReference xsi:type="typens:ProjectedCoordinateSystem">
        <WKT>PROJCS["NAD_1983_2011_Oregon_Statewide_Lambert_Ft_Intl",GEOGCS["GCS_NAD_1983_2011",DATUM["D_NAD_1983_2011",SPHEROID["GRS_1980",6378137.0,298.257222101]],PRIMEM["Greenwich",0.0],UNIT["Degree",0.0174532925199433]],PROJECTION["Lambert_Conformal_Conic"],PARAMETER["False_Easting",1312335.958005249],PARAMETER["False_Northing",0.0],PARAMETER["Central_Meridian",-120.5],PARAMETER["Standard_Parallel_1",43.0],PARAMETER["Standard_Parallel_2",45.5],PARAMETER["Latitude_Of_Origin",41.75],UNIT["Foot",0.3048],AUTHORITY["EPSG",6557]]</WKT>
        <XOrigin>-118489100</XOrigin>
        <YOrigin>-97381100</YOrigin>
        <XYScale>37592196.316242374</XYScale>
        <ZOrigin>0</ZOrigin>
        <ZScale>1</ZScale>
        <MOrigin>-100000</MOrigin>
        <MScale>10000</MScale>
        <XYTolerance>0.0032808398950131233</XYTolerance>
        <ZTolerance>2</ZTolerance>
        <MTolerance>0.001</MTolerance>
        <HighPrecision>true</HighPrecision>
        <WKID>102970</WKID>
        <LatestWKID>6557</LatestWKID>
      </SpatialReference>
      <SourceGCPs xsi:type="typens:ArrayOfDouble">
        <Double>2.1982834778348206</Double>
        <Double>2.7951679531638547</Double>
        <Double>15.614931013213891</Double>
        <Double>1.0817749018247014</Double>
        <Double>12.575086224663737</Double>
        <Double>16.483014251378791</Double>
        <Double>15.513693725927741</Double>
        <Double>16.355469095113676</Double>
      </SourceGCPs>
      <TargetGCPs xsi:type="typens:ArrayOfDouble">
        <Double>625324.07578739524</Double>
        <Double>1506435.3641732337</Double>
        <Double>630691.8917322905</Double>
        <Double>1505753.6564960629</Double>
        <Double>629473.65124672651</Double>
        <Double>1511912.0656168014</Double>
        <Double>630649.31397637725</Double>
        <Double>1511861.826115489</Double>
      </TargetGCPs>
      <Name />
    </GeodataXform>
  </Metadata>
  <PAMRasterBand band="1">
    <Histograms>
      <HistItem>
        <HistMin>-0.5</HistMin>
        <HistMax>255.5</HistMax>
        <BucketCount>256</BucketCount>
        <IncludeOutOfRange>1</IncludeOutOfRange>
        <Approximate>0</Approximate>
        <HistCounts>1021984|0|0|0|0|0|0|0|0|0|0|0|0|0|0|0|0|0|0|0|0|0|0|179205|0|0|0|0|0|0|0|0|0|0|0|0|0|0|0|0|0|0|0|0|0|0|0|0|0|1|0|0|0|0|0|0|1038587|0|90|0|0|0|0|0|0|0|0|0|59850|0|0|0|0|0|0|0|28204|0|0|0|0|0|0|0|0|0|0|0|1|0|0|0|0|0|0|0|0|0|0|0|0|0|206|0|83817|0|0|0|0|0|8180|0|0|0|0|795|0|0|0|0|0|0|0|0|0|0|0|0|0|0|0|0|0|0|0|0|0|0|0|0|0|0|0|0|296|0|0|0|0|0|0|0|0|0|0|0|65030|0|0|0|0|0|0|0|0|0|0|0|0|0|7|0|0|0|0|0|0|0|16340|0|0|0|162|0|0|0|0|0|0|2|0|0|0|0|0|0|0|130173|0|0|0|0|0|0|8|0|0|0|0|0|0|0|0|0|0|0|0|0|13|122|0|0|0|0|0|16409748|0|0|0|0|734326|5|0|0|0|0|0|0|0|0|0|0|0|4|0|32459|0|101806|0|0|0|0|0|0|0|12450543</HistCounts>
      </HistItem>
    </Histograms>
  </PAMRasterBand>
  <PAMRasterBand band="2">
    <Histograms>
      <HistItem>
        <HistMin>-0.5</HistMin>
        <HistMax>255.5</HistMax>
        <BucketCount>256</BucketCount>
        <IncludeOutOfRange>1</IncludeOutOfRange>
        <Approximate>0</Approximate>
        <HistCounts>1375608|0|0|0|0|0|0|0|0|0|0|0|0|0|0|0|0|0|0|0|0|0|0|0|0|0|0|0|0|0|0|0|0|0|0|0|0|0|0|0|0|0|0|0|0|0|0|0|0|0|0|0|0|0|0|0|0|0|77|0|0|0|0|0|0|0|0|0|0|0|0|0|0|0|0|0|0|121393|0|59850|0|1|0|0|0|0|0|0|1|0|0|0|0|0|0|0|0|0|0|0|0|0|80|0|83817|0|0|0|0|0|8180|0|0|8|0|0|0|0|0|0|0|0|0|0|0|0|0|0|0|0|0|0|3|0|0|0|0|0|0|0|0|0|0|0|352|0|0|4|0|0|0|0|633134|0|0|0|65030|0|0|0|0|11|0|0|101806|0|0|0|1217792|0|0|0|0|0|9|0|0|0|16340|0|0|0|195|0|0|0|5|0|32459|0|0|0|0|0|0|0|0|0|18250|0|0|0|0|0|0|0|0|0|0|0|0|0|0|0|0|0|0|0|0|134|0|0|0|0|0|16409748|0|0|0|0|0|0|0|0|0|0|0|0|0|0|0|0|0|0|0|0|0|0|0|0|0|0|0|0|0|12217677</HistCounts>
      </HistItem>
    </Histograms>
  </PAMRasterBand>
  <PAMRasterBand band="3">
    <Histograms>
      <HistItem>
        <HistMin>-0.5</HistMin>
        <HistMax>255.5</HistMax>
        <BucketCount>256</BucketCount>
        <IncludeOutOfRange>1</IncludeOutOfRange>
        <Approximate>0</Approximate>
        <HistCounts>2990747|0|0|0|0|0|0|0|0|0|0|0|0|0|0|0|0|0|0|1|0|0|0|0|0|0|0|0|0|0|0|0|0|0|6|0|0|0|0|0|0|0|0|0|0|0|0|0|9|1|1|0|0|0|0|0|0|0|100|0|0|6|0|0|0|0|0|0|0|0|0|0|0|12|0|32459|0|0|0|0|0|0|0|0|0|18248|0|0|0|0|0|0|0|0|0|0|0|0|0|0|0|0|140|0|83817|0|0|0|0|0|8180|0|0|0|0|28204|0|0|0|0|0|0|0|0|0|0|0|0|0|0|0|0|0|0|0|0|0|59850|0|0|0|0|0|0|196|0|0|0|0|0|0|0|0|0|0|0|65030|0|0|0|0|0|0|0|0|0|0|0|121393|0|0|0|0|0|0|0|0|0|16340|0|0|0|195|0|0|0|0|0|0|0|0|0|0|0|0|0|0|0|0|0|0|0|0|0|0|0|0|0|0|0|0|0|0|0|0|0|0|0|0|353|0|0|0|0|0|16409748|0|0|0|0|0|0|179205|0|0|0|0|0|0|0|0|0|0|0|0|0|0|0|0|0|0|0|0|0|0|12347723</HistCounts>
      </HistItem>
    </Histograms>
  </PAMRasterBand>
</PAMDataset>
